{
	"_version": "1.1.0",
	"resources": [
		{
			"name": ".theming",
			"size": 94,
			"theme": "sap_fiori_3_hcb"
		},
		{
			"name": "ActionMode.less",
			"size": 706,
			"designtime": true,
			"theme": "sap_fiori_3_hcb"
		},
		{
			"name": "AnchorItem.less",
			"size": 1794,
			"designtime": true,
			"theme": "sap_fiori_3_hcb"
		},
		{
			"name": "AnchorNavigationBar.less",
			"size": 487,
			"designtime": true,
			"theme": "sap_fiori_3_hcb"
		},
		{
			"name": "ApplicationContainer.less",
			"size": 293,
			"designtime": true,
			"theme": "sap_fiori_3_hcb"
		},
		{
			"name": "Catalog.less",
			"size": 815,
			"designtime": true,
			"theme": "sap_fiori_3_hcb"
		},
		{
			"name": "ContactSupport.less",
			"size": 647,
			"designtime": true,
			"theme": "sap_fiori_3_hcb"
		},
		{
			"name": "DynamicTile.less",
			"size": 2296,
			"designtime": true,
			"theme": "sap_fiori_3_hcb"
		},
		{
			"name": "GroupList.less",
			"size": 2638,
			"designtime": true,
			"theme": "sap_fiori_3_hcb"
		},
		{
			"name": "LoadingDialog.less",
			"size": 407,
			"designtime": true,
			"theme": "sap_fiori_3_hcb"
		},
		{
			"name": "MeArea.less",
			"size": 358,
			"designtime": true,
			"theme": "sap_fiori_3_hcb"
		},
		{
			"name": "Notifications.less",
			"size": 99,
			"designtime": true,
			"theme": "sap_fiori_3_hcb"
		},
		{
			"name": "PictureTile.less",
			"size": 327,
			"designtime": true,
			"theme": "sap_fiori_3_hcb"
		},
		{
			"name": "PlusTile.less",
			"size": 692,
			"designtime": true,
			"theme": "sap_fiori_3_hcb"
		},
		{
			"name": "SearchPieChart.less",
			"size": 161,
			"designtime": true,
			"theme": "sap_fiori_3_hcb"
		},
		{
			"name": "ShellFloatingAction.less",
			"size": 851,
			"designtime": true,
			"theme": "sap_fiori_3_hcb"
		},
		{
			"name": "ShellHeader.less",
			"size": 4365,
			"designtime": true,
			"theme": "sap_fiori_3_hcb"
		},
		{
			"name": "SplitContainer.less",
			"size": 74,
			"designtime": true,
			"theme": "sap_fiori_3_hcb"
		},
		{
			"name": "Tile.less",
			"size": 584,
			"designtime": true,
			"theme": "sap_fiori_3_hcb"
		},
		{
			"name": "TileBase.less",
			"size": 2066,
			"designtime": true,
			"theme": "sap_fiori_3_hcb"
		},
		{
			"name": "TileContainer.less",
			"size": 4198,
			"designtime": true,
			"theme": "sap_fiori_3_hcb"
		},
		{
			"name": "TileState.less",
			"size": 427,
			"designtime": true,
			"theme": "sap_fiori_3_hcb"
		},
		{
			"name": "UserPreferencesButton.less",
			"size": 156,
			"designtime": true,
			"theme": "sap_fiori_3_hcb"
		},
		{
			"name": "css_variables.css",
			"size": 16631,
			"theme": "sap_fiori_3_hcb"
		},
		{
			"name": "css_variables.less",
			"size": 110383,
			"designtime": true,
			"theme": "sap_fiori_3_hcb"
		},
		{
			"name": "css_variables.source.less",
			"size": 110013,
			"designtime": true,
			"theme": "sap_fiori_3_hcb"
		},
		{
			"name": "flower-standalone.less",
			"size": 1009,
			"designtime": true,
			"theme": "sap_fiori_3_hcb"
		},
		{
			"name": "library-RTL.css",
			"size": 178691,
			"theme": "sap_fiori_3_hcb"
		},
		{
			"name": "library-parameters.json",
			"size": 6959,
			"theme": "sap_fiori_3_hcb"
		},
		{
			"name": "library.css",
			"size": 178625,
			"theme": "sap_fiori_3_hcb"
		},
		{
			"name": "library.less",
			"size": 27362,
			"designtime": true,
			"theme": "sap_fiori_3_hcb"
		},
		{
			"name": "library.source.less",
			"size": 914,
			"designtime": true,
			"theme": "sap_fiori_3_hcb"
		},
		{
			"name": "library_skeleton-RTL.css",
			"size": 182073,
			"theme": "sap_fiori_3_hcb"
		},
		{
			"name": "library_skeleton.css",
			"size": 182007,
			"theme": "sap_fiori_3_hcb"
		}
	]
}