<core:FragmentDefinition
	xmlns:template="http://schemas.sap.com/sapui5/extension/sap.ui.core.template/1"
	xmlns:unittest="http://schemas.sap.com/sapui5/preprocessorextension/sap.fe.unittesting/1"
	xmlns:macrodata="http://schemas.sap.com/sapui5/extension/sap.ui.core.CustomData/1"
	xmlns:core="sap.ui.core"
	xmlns:control="sap.fe.core.controls"
	xmlns="sap.m"
	template:require="{
				MODEL: 'sap/ui/model/odata/v4/AnnotationHelper',
				FIELD: 'sap/fe/macros/field/FieldHelper'
				}"
>
	<template:if test="{dataField>}">
		<VBox class="sapUiTinyMarginTopBottom" binding="{semantic>/navigationPath}">
			<template:if test="{= ${dataField>IconUrl@@MODEL.value} !== undefined }">
				<template:then>
					<control:ConditionalWrapper
						core:require="{FieldRuntime: 'sap/fe/macros/field/FieldRuntime'}"
						condition="{= FIELD.checkPrimaryActions(${semantic>}) }"
					>
						<control:contentTrue>
							<control:CustomQuickViewPage
								unittest:id="CustomQuickViewPageIconUrlTest"
								icon="{dataField>IconUrl@@MODEL.value}"
								fallbackIcon="sap-icon://product"
								title="{dataField>Value@@MODEL.format}"
								macrodata:titleLink="{= FIELD.getPrimaryAction(${semantic>}) }"
								description="{= (${dataField>Label}) ? ${dataField>Label} : ${dataField>Value/$Path@com.sap.vocabularies.Common.v1.Label} }"
							>
							</control:CustomQuickViewPage>
						</control:contentTrue>
						<control:contentFalse>
							<control:CustomQuickViewPage
								unittest:id="CustomQuickViewPageIconUrlTestNoLinkTitle"
								icon="{dataField>IconUrl@@MODEL.value}"
								fallbackIcon="sap-icon://product"
								title="{dataField>Value@@MODEL.format}"
								description="{= (${dataField>Label}) ? ${dataField>Label} : ${dataField>Value/$Path@com.sap.vocabularies.Common.v1.Label} }"
							>
							</control:CustomQuickViewPage>
						</control:contentFalse>
					</control:ConditionalWrapper>
				</template:then>
				<template:elseif test="{= ${dataField>Value@@MODEL.value} !== undefined}">
					<control:ConditionalWrapper
						core:require="{FieldRuntime: 'sap/fe/macros/field/FieldRuntime'}"
						condition="{= FIELD.checkPrimaryActions(${semantic>}) }"
					>
						<control:contentTrue>
							<control:CustomQuickViewPage
								unittest:id="CustomQuickViewPageTest"
								title="{dataField>Value@@MODEL.format}"
								macrodata:titleLink="{= FIELD.getPrimaryAction(${semantic>}) }"
								description="{= (${dataField>Label}) ? ${dataField>Label} : ${dataField>Value/$Path@com.sap.vocabularies.Common.v1.Label} }"
							>
							</control:CustomQuickViewPage>
						</control:contentTrue>
						<control:contentFalse>
							<control:CustomQuickViewPage
								unittest:id="CustomQuickViewPageTestNoLinkTitle"
								title="{dataField>Value@@MODEL.format}"
								description="{= (${dataField>Label}) ? ${dataField>Label} : ${dataField>Value/$Path@com.sap.vocabularies.Common.v1.Label} }"
							>
							</control:CustomQuickViewPage>
						</control:contentFalse>
					</control:ConditionalWrapper>
				</template:elseif>
				<template:else>
					<control:ConditionalWrapper
						core:require="{FieldRuntime: 'sap/fe/macros/field/FieldRuntime'}"
						condition="{= FIELD.checkPrimaryActions(${semantic>}) }"
					>
						<control:contentTrue>
							<control:CustomQuickViewPage
								unittest:id="CustomQuickViewNoFieldValuePageTest"
								title="{dataField>@@MODEL.format}"
								macrodata:titleLink="{= FIELD.getPrimaryAction(${semantic>}) }"
								description="{= (${dataField>Label}) ? ${dataField>Label} : ${dataField>Value/$Path@com.sap.vocabularies.Common.v1.Label} }"
							>
							</control:CustomQuickViewPage>
						</control:contentTrue>
						<control:contentFalse>
							<control:CustomQuickViewPage
								unittest:id="CustomQuickViewNoFieldValuePageTestNoLinkTitle"
								title="{dataField>@@MODEL.format}"
								description="{= (${dataField>Label}) ? ${dataField>Label} : ${dataField>Value/$Path@com.sap.vocabularies.Common.v1.Label} }"
							>
							</control:CustomQuickViewPage>
						</control:contentFalse>
					</control:ConditionalWrapper>
				</template:else>
			</template:if>
		</VBox>
	</template:if>
</core:FragmentDefinition>
