{
	"_version": "1.1.0",
	"resources": [
		{
			"name": ".theming",
			"size": 90,
			"theme": "sap_fiori_3"
		},
		{
			"name": "css_variables.css",
			"size": 401,
			"theme": "sap_fiori_3"
		},
		{
			"name": "css_variables.less",
			"size": 94372,
			"designtime": true,
			"theme": "sap_fiori_3"
		},
		{
			"name": "css_variables.source.less",
			"size": 94004,
			"designtime": true,
			"theme": "sap_fiori_3"
		},
		{
			"name": "library-RTL.css",
			"size": 38412,
			"theme": "sap_fiori_3"
		},
		{
			"name": "library-parameters.json",
			"size": 2,
			"theme": "sap_fiori_3"
		},
		{
			"name": "library.css",
			"size": 38389,
			"theme": "sap_fiori_3"
		},
		{
			"name": "library.less",
			"size": 432,
			"designtime": true,
			"theme": "sap_fiori_3"
		},
		{
			"name": "library.source.less",
			"size": 245,
			"designtime": true,
			"theme": "sap_fiori_3"
		},
		{
			"name": "library_skeleton-RTL.css",
			"size": 40401,
			"theme": "sap_fiori_3"
		},
		{
			"name": "library_skeleton.css",
			"size": 40378,
			"theme": "sap_fiori_3"
		}
	]
}